nigerian_airline_scrapper/__init__.py
nigerian_airline_scrapper/scrapper.py
nigerian_airline_scrapper/custom/__init__.py
nigerian_airline_scrapper/custom/exceptions.py
nigerian_airline_scrapper/custom/thread.py
nigerian_airline_scrapper/flights/__init__.py
nigerian_airline_scrapper/flights/dana.py
nigerian_airline_scrapper-0.2.3.dist-info/METADATA
nigerian_airline_scrapper-0.2.3.dist-info/WHEEL
nigerian_airline_scrapper-0.2.3.dist-info/licenses/LICENSE
nigerian_airline_scrapper-0.2.3.dist-info/RECORD
