Metadata-Version: 2.1
Name: nigerian-airline-scrapper
Version: 0.2.3
Author-email: Atinuke <Ayoyinkaomotoso@gmail.com>
License:                     GNU GENERAL PUBLIC LICENSE
License-File: LICENSE
Keywords: airline,nigerian,scrapper
Classifier: License :: OSI Approved :: MIT License
Classifier: Programming Language :: Python
Classifier: Programming Language :: Python :: 3
Requires-Python: >=3.6
Requires-Dist: beautifulsoup4
Requires-Dist: feedparser>=5.2.0
Requires-Dist: html2text
Requires-Dist: lxml
Requires-Dist: requests
Requires-Dist: tomli; python_version < '3.11'
